alignments/__init__.py
alignments/dataset.py
alignments/datasets/__init__.py
alignments/datasets/libritts.py
alignments-0.1.7.dist-info/WHEEL
alignments-0.1.7.dist-info/METADATA
alignments-0.1.7.dist-info/RECORD
