Metadata-Version: 2.1
Name: alignments
Version: 0.1.7
Summary: A library for aligning audio and text
Author-email: Christoph Minixhofer <christoph.minixhofer@gmail.com>
Requires-Python: >=3.6
Requires-Dist: click>=8.0.4
Requires-Dist: librosa>=0.9.2
Requires-Dist: numpy>=1.19.5
Requires-Dist: rich>=10.11.0
Requires-Dist: soundfile>=0.12.1
Requires-Dist: textgrid>=1.5
Requires-Dist: torch>=1.4.0
Requires-Dist: tqdm>=4.64.0
Project-URL: homepage, https://github.com/MiniXC/alignments
